jupytergis/__init__.py
jupytergis_lite-0.11.1.dist-info/METADATA
jupytergis_lite-0.11.1.dist-info/WHEEL
jupytergis_lite-0.11.1.dist-info/licenses/LICENSE
jupytergis_lite-0.11.1.dist-info/RECORD
